{
    "1460567609": {
        "count": 0,
        "values": {},
        "qr_codes": {
            "next_qr_id": 3,
            "codes": []
        }
    },
    "6944022441": {
        "count": 0,
        "values": {},
        "qr_codes": {
            "next_qr_id": 2,
            "codes": [
                {
                    "id": 1,
                    "text": "23455555",
                    "filepath": "qrcodes\\qr_user6944022441_id1.png"
                }
            ]
        }
    },
    "6306673814": {
        "count": 0,
        "values": {},
        "qr_codes": {
            "next_qr_id": 1,
            "codes": []
        }
    }
}